docs/__init__.py
docs/conf.py
dwbzen/__init__.py
dwbzen/chain_test.py
dwbzen/geo_test.py
dwbzen/path_titles.py
dwbzen/common/__init__.py
dwbzen/common/__version__.py
dwbzen/common/characterCollector.py
dwbzen/common/characterCollectorRunner.py
dwbzen/common/collector.py
dwbzen/common/collectorProducer.py
dwbzen/common/environment.py
dwbzen/common/geometry.py
dwbzen/common/markovChain.py
dwbzen/common/producer.py
dwbzen/common/ruleSet.py
dwbzen/common/sentenceProducer.py
dwbzen/common/sentenceProducerRunner.py
dwbzen/common/substitutionSystem.py
dwbzen/common/textParser.py
dwbzen/common/utils.py
dwbzen/common/wordCollector.py
dwbzen/common/wordCollectorRunner.py
dwbzen/common/wordProducer.py
dwbzen/common/wordProducerRunner.py
dwbzen/music/__init__.py
dwbzen/music/__version__.py
dwbzen/music/chord.py
dwbzen/music/chords.py
dwbzen/music/durationCollector.py
dwbzen/music/instruments.py
dwbzen/music/intervalCollector.py
dwbzen/music/intervalCollectorRunner.py
dwbzen/music/keys.py
dwbzen/music/musicCollector.py
dwbzen/music/musicProducer.py
dwbzen/music/musicProducerRunner.py
dwbzen/music/musicScale.py
dwbzen/music/musicSubstitutionRules.py
dwbzen/music/musicSubstitutionSystem.py
dwbzen/music/musicUtils.py
dwbzen/music/noteCollector.py
dwbzen/music/noteCollectorRunner.py
dwbzen/music/sample_usage.py
dwbzen/music/scale.py
dwbzen/music/scales.py
dwbzen/music/scoreGen.py
dwbzen/music/scoreGenRunner.py
dwbzen/music/song.py
dwbzen-0.1.2.data/data/resources/2of12pos.txt
dwbzen-0.1.2.data/data/resources/3eslpos.txt
dwbzen-0.1.2.data/data/resources/5deskpos.txt
dwbzen-0.1.2.data/data/resources/allChordFormulas.json
dwbzen-0.1.2.data/data/resources/clefs.json
dwbzen-0.1.2.data/data/resources/commonScaleFormulas.json
dwbzen-0.1.2.data/data/resources/common_scaleFormulas.json
dwbzen-0.1.2.data/data/resources/drugBrandNames.txt
dwbzen-0.1.2.data/data/resources/instruments.json
dwbzen-0.1.2.data/data/resources/keys.json
dwbzen-0.1.2.data/data/resources/substitution_rules.json
dwbzen-0.1.2.dist-info/LICENSE.txt
dwbzen-0.1.2.dist-info/METADATA
dwbzen-0.1.2.dist-info/WHEEL
dwbzen-0.1.2.dist-info/namespace_packages.txt
dwbzen-0.1.2.dist-info/top_level.txt
dwbzen-0.1.2.dist-info/RECORD
