Metadata-Version: 2.1
Name: dwbzen
Version: 0.1.2
Summary: Music and Math package including MarkovChain generation from text and music source, and production
Home-page: https://github.com/dwbzen/dwbzen
Author: Don Bacon
Author-email: dwbzen@gmail.com
Maintainer: Donald Bacon
Maintainer-email: dwbzen@gmail.com
License: MIT
Keywords: markov chain text music
Platform: UNKNOWN
Classifier: Development Status :: 3 - Alpha
Classifier: Intended Audience :: Developers
Classifier: Environment :: Console
Classifier: Programming Language :: Python :: 3
Classifier: License :: OSI Approved :: MIT License
Classifier: Operating System :: OS Independent
Classifier: Programming Language :: Python :: 3.9
Classifier: Programming Language :: Python :: 3.10
Requires-Python: >=3.8
License-File: LICENSE.txt
Requires-Dist: music21 (>=7.1.0)
Requires-Dist: pandas (>=1.4.3)
